autodot/__init__.py
autodot-0.1.0.dist-info/LICENSE
autodot-0.1.0.dist-info/WHEEL
autodot-0.1.0.dist-info/METADATA
autodot-0.1.0.dist-info/RECORD
