Metadata-Version: 2.1
Name: autodot
Version: 0.1.0
Summary: Automated dotfile management using Python & Python/Click!
Home-page: https://github.com/aubricus
License: MIT
Author: Aubrey Taylor
Requires-Python: >=3.6,<3.9
Classifier: License :: OSI Approved :: MIT License
Classifier: Programming Language :: Python :: 3
Classifier: Programming Language :: Python :: 3.6
Classifier: Programming Language :: Python :: 3.7
Classifier: Programming Language :: Python :: 3.8
Project-URL: Documentation, https://aubricus.github.io/autodot/
Project-URL: Repository, https://github.com/aubricus
